mcp_sqlalchemy_server/__init__.py
mcp_sqlalchemy_server/server.py
iflow_mcp_mcp_sqlalchemy_server-0.3.1.dist-info/METADATA
iflow_mcp_mcp_sqlalchemy_server-0.3.1.dist-info/WHEEL
iflow_mcp_mcp_sqlalchemy_server-0.3.1.dist-info/entry_points.txt
iflow_mcp_mcp_sqlalchemy_server-0.3.1.dist-info/licenses/LICENSE
iflow_mcp_mcp_sqlalchemy_server-0.3.1.dist-info/RECORD
