Metadata-Version: 2.4
Name: iflow-mcp_mcp-sqlalchemy-server
Version: 0.3.1
Summary: A simple MCP ODBC server using FastAPI and ODBC
Author-email: Sergey Malinin <sergmalinin@gmail.com>
License-File: LICENSE
Requires-Python: >=3.10
Requires-Dist: mcp[cli]>=1.4.1
Requires-Dist: pyodbc>=5.2.0
Requires-Dist: python-dotenv>=1.0.1
